{
  "id": "9fb6bf2c-87b7-46a2-8ca8-01b5b5e28841",
  "prevId": "00000000-0000-0000-0000-000000000000",
  "version": "7",
  "dialect": "postgresql",
  "tables": {
    "public.secrets": {
      "name": "secrets",
      "schema": "",
      "columns": {
        "id": {
          "name": "id",
          "type": "serial",
          "primaryKey": true,
          "notNull": true
        },
        "secret_key": {
          "name": "secret_key",
          "type": "varchar(66)",
          "primaryKey": false,
          "notNull": true
        },
        "voting_contract_id": {
          "name": "voting_contract_id",
          "type": "integer",
          "primaryKey": false,
          "notNull": true
        }
      },
      "indexes": {},
      "foreignKeys": {
        "secrets_voting_contract_id_votingContracts_id_fk": {
          "name": "secrets_voting_contract_id_votingContracts_id_fk",
          "tableFrom": "secrets",
          "tableTo": "votingContracts",
          "columnsFrom": [
            "voting_contract_id"
          ],
          "columnsTo": [
            "id"
          ],
          "onDelete": "cascade",
          "onUpdate": "no action"
        }
      },
      "compositePrimaryKeys": {},
      "uniqueConstraints": {},
      "policies": {},
      "checkConstraints": {},
      "isRLSEnabled": false
    },
    "public.votingContracts": {
      "name": "votingContracts",
      "schema": "",
      "columns": {
        "id": {
          "name": "id",
          "type": "serial",
          "primaryKey": true,
          "notNull": true
        },
        "market_id": {
          "name": "market_id",
          "type": "bigint",
          "primaryKey": false,
          "notNull": true
        },
        "option_a": {
          "name": "option_a",
          "type": "bigint",
          "primaryKey": false,
          "notNull": true
        },
        "option_b": {
          "name": "option_b",
          "type": "bigint",
          "primaryKey": false,
          "notNull": true
        },
        "rewards": {
          "name": "rewards",
          "type": "bigint",
          "primaryKey": false,
          "notNull": true
        },
        "start_timestamp": {
          "name": "start_timestamp",
          "type": "bigint",
          "primaryKey": false,
          "notNull": true
        },
        "end_timestamp": {
          "name": "end_timestamp",
          "type": "bigint",
          "primaryKey": false,
          "notNull": true
        },
        "threshold_votes": {
          "name": "threshold_votes",
          "type": "integer",
          "primaryKey": false,
          "notNull": true
        },
        "hbar_locking_contract_address": {
          "name": "hbar_locking_contract_address",
          "type": "varchar(66)",
          "primaryKey": false,
          "notNull": true
        },
        "n": {
          "name": "n",
          "type": "varchar(1024)",
          "primaryKey": false,
          "notNull": true
        },
        "t": {
          "name": "t",
          "type": "bigint",
          "primaryKey": false,
          "notNull": true
        },
        "a": {
          "name": "a",
          "type": "integer",
          "primaryKey": false,
          "notNull": true
        },
        "sk_locked": {
          "name": "sk_locked",
          "type": "varchar(66)",
          "primaryKey": false,
          "notNull": true
        },
        "hashed_sk": {
          "name": "hashed_sk",
          "type": "varchar(66)",
          "primaryKey": false,
          "notNull": true
        },
        "contract_address": {
          "name": "contract_address",
          "type": "varchar(66)",
          "primaryKey": false,
          "notNull": true
        },
        "verified": {
          "name": "verified",
          "type": "boolean",
          "primaryKey": false,
          "notNull": true,
          "default": false
        },
        "server": {
          "name": "server",
          "type": "boolean",
          "primaryKey": false,
          "notNull": true,
          "default": false
        }
      },
      "indexes": {},
      "foreignKeys": {},
      "compositePrimaryKeys": {},
      "uniqueConstraints": {},
      "policies": {},
      "checkConstraints": {},
      "isRLSEnabled": false
    }
  },
  "enums": {},
  "schemas": {},
  "sequences": {},
  "roles": {},
  "policies": {},
  "views": {},
  "_meta": {
    "columns": {},
    "schemas": {},
    "tables": {}
  }
}